solarius/.DS_Store
solarius/__init__.py
solarius/model.py
solarius/py.typed
solarius/requirements.txt
solarius-0.1.2.dist-info/WHEEL
solarius-0.1.2.dist-info/METADATA
solarius-0.1.2.dist-info/RECORD
