Metadata-Version: 2.3
Name: solarius
Version: 0.1.2
Summary: Python library for calculating precise solar returns
Author: Chinmay Kakatkar
License: MIT License
Requires-Dist: geopy>=2.4.1
Requires-Dist: pytz>=2025.2
Requires-Dist: skyfield>=1.53
Requires-Dist: timezonefinder>=8.0.0
Requires-Python: >=3.12
Project-URL: Homepage, https://github.com/ckstash/solarius
